[
    {
        "name": "Boo",
        "type": "consumable",
        "increment": 1,
        "max_quantity": 50,
        "overlay_background": "#000000",
        "img": "images/minor checks/boo.png",
        "codes": "booCount"
    },
    {
        "name": "Butler's Room Boo (PeekaBoo)",
        "type": "toggle",
        "codes": "butlerBoo"
    },
    {
        "name": "Hidden Room Boo (GumBoo)",
        "type": "static",
        "codes": "hiddenBoo"
    },
    {
        "name": "Fortune Teller Boo (Booigi)",
        "type": "static",
        "codes": "fortuneBoo"
    },
    {
        "name": "Mirror Room Boo (Kung Boo)",
        "type": "static",
        "codes": "mirrorBoo"
    },
    {
        "name": "Laundry Room Boo (Boogie)",
        "type": "static",
        "codes": "laundryBoo"
    },
    {
        "name": "Kitchen Boo (Booligan)",
        "type": "static",
        "codes": "kitchenBoo"
    },
    {
        "name": "Dining Room Boo (Boodacious)",
        "type": "static",
        "codes": "diningBoo"
    },
    {
        "name": "Ball Room Boo (Boo La La)",
        "type": "static",
        "codes": "ballBoo"
    },
    {
        "name": "Billiards Boo (Boohoo)",
        "type": "static",
        "codes": "billiardBoo"
    },
    {
        "name": "Projection Room Boo (ShamBoo)",
        "type": "static",
        "codes": "projectionBoo"
    },
    {
        "name": "Storage Room Boo (Game Boo)",
        "type": "static",
        "codes": "storageBoo"
    },
    {
        "name": "Conservatory Boo (Boomeo)",
        "type": "static",
        "codes": "conservatoryBoo"
    },
    {
        "name": "Rec Room Boo (Booregard)",
        "type": "static",
        "codes": "recBoo"
    },
    {
        "name": "Nursery Boo (TurBoo)",
        "type": "static",
        "codes": "nurseryBoo"
    },
    {
        "name": "Twin's Room Boo (Booris)",
        "type": "static",
        "codes": "twinBoo"
    },
    {
        "name": "Sitting Room Boo (Boolivia)",
        "type": "static",
        "codes": "sittingBoo"
    },
    {
        "name": "Guest Room Boo (Boonita)",
        "type": "static",
        "codes": "guestBoo"
    },
    {
        "name": "Master Bedroom Boo (Boolicious)",
        "type": "static",
        "codes": "masterBoo"
    },
    {
        "name": "Study Boo (TaBoo)",
        "type": "static",
        "codes": "studyBoo"
    },
    {
        "name": "Parlor Boo (BamBoo)",
        "type": "static",
        "codes": "parlorBoo"
    },
    {
        "name": "Wardrobe Boo (GameBoo Advance)",
        "type": "static",
        "codes": "wardrobeBoo"
    },
    {
        "name": "Anteroom Boo (Bootha)",
        "type": "static",
        "codes": "anteroomBoo"
    },
    {
        "name": "Astral Boo (Boonswoggle)",
        "type": "static",
        "codes": "astralBoo"
    },
    {
        "name": "Nana's Room (LamBooger)",
        "type": "static",
        "codes": "nanaBoo"
    },
    {
        "name": "Tea Room Boo (Mr. Boojangles)",
        "type": "static",
        "codes": "teaBoo"
    },
    {
        "name": "Armory Boo (Underboo)",
        "type": "static",
        "codes": "armoryBoo"
    },
    {
        "name": "Telephone Room Boo (Boomerang)",
        "type": "static",
        "codes": "teleBoo"
    },
    {
        "name": "Safari Room Boo (Little Boo Peep)",
        "type": "static",
        "codes": "safariBoo"
    },
    {
        "name": "Ceramics Studio Boo (TamBoorine)",
        "type": "static",
        "codes": "ceramicsBoo"
    },
    {
        "name": "Clockwork Room Boo (Booscaster)",
        "type": "static",
        "codes": "clockworkBoo"
    },
    {
        "name": "Artist's Studio Boo (Bootique)",
        "type": "static",
        "codes": "artistBoo"
    },
    {
        "name": "Cold Storage Boo (Boolderdash)",
        "type": "static",
        "codes": "coldBoo"
    },
    {
        "name": "Cellar Boo (Booripedes)",
        "type": "static",
        "codes": "cellarBoo"
    },
    {
        "name": "Pipe Room Boo (Booffant)",
        "type": "static",
        "codes": "pipeBoo"
    },
    {
        "name": "Breaker Room Boo (Boo B. Hatch)",
        "type": "static",
        "codes": "breakerBoo"
    },
    {
        "name": "Boolossus Boo 1",
        "type": "static",
        "codes": "bool1"
    },
    {
        "name": "Boolossus Boo 2",
        "type": "static",
        "codes": "bool2"
    },
    {
        "name": "Boolossus Boo 3",
        "type": "static",
        "codes": "bool3"
    },
    {
        "name": "Boolossus Boo 4",
        "type": "static",
        "codes": "bool4"
    },
    {
        "name": "Boolossus Boo 5",
        "type": "static",
        "codes": "bool5"
    },
    {
        "name": "Boolossus Boo 6",
        "type": "static",
        "codes": "bool6"
    },
    {
        "name": "Boolossus Boo 7",
        "type": "static",
        "codes": "bool7"
    },
    {
        "name": "Boolossus Boo 8",
        "type": "static",
        "codes": "bool8"
    },
    {
        "name": "Boolossus Boo 9",
        "type": "static",
        "codes": "bool9"
    },
    {
        "name": "Boolossus Boo 10",
        "type": "static",
        "codes": "bool10"
    },
    {
        "name": "Boolossus Boo 11",
        "type": "static",
        "codes": "bool11"
    },
    {
        "name": "Boolossus Boo 12",
        "type": "static",
        "codes": "bool12"
    },
    {
        "name": "Boolossus Boo 13",
        "type": "static",
        "codes": "bool13"
    },
    {
        "name": "Boolossus Boo 14",
        "type": "static",
        "codes": "bool14"
    },
    {
        "name": "Boolossus Boo 15",
        "type": "static",
        "codes": "bool15"
    }
]